torchdata/__init__.py
torchdata/version.py
torchdata/nodes/__init__.py
torchdata/nodes/_apply_udf.py
torchdata/nodes/_populate_queue.py
torchdata/nodes/adapters.py
torchdata/nodes/base_node.py
torchdata/nodes/batch.py
torchdata/nodes/constants.py
torchdata/nodes/exception_wrapper.py
torchdata/nodes/loader.py
torchdata/nodes/map.py
torchdata/nodes/pin_memory.py
torchdata/nodes/prefetch.py
torchdata/nodes/snapshot_store.py
torchdata/nodes/types.py
torchdata/nodes/samplers/__init__.py
torchdata/nodes/samplers/multi_node_weighted_sampler.py
torchdata/nodes/samplers/stop_criteria.py
torchdata/nodes/samplers/utils.py
torchdata/stateful_dataloader/__init__.py
torchdata/stateful_dataloader/incremental_state.py
torchdata/stateful_dataloader/sampler.py
torchdata/stateful_dataloader/stateful.py
torchdata/stateful_dataloader/stateful_dataloader.py
torchdata/stateful_dataloader/worker.py
torchdata-0.10.1.dist-info/LICENSE
torchdata-0.10.1.dist-info/METADATA
torchdata-0.10.1.dist-info/WHEEL
torchdata-0.10.1.dist-info/top_level.txt
torchdata-0.10.1.dist-info/RECORD
