Metadata-Version: 2.1
Name: torchdata
Version: 0.10.1
Summary: Composable data loading modules for PyTorch
Home-page: https://github.com/pytorch/data
Author: PyTorch Team
Author-email: packages@pytorch.org
License: BSD
Classifier: Intended Audience :: Developers
Classifier: Intended Audience :: Science/Research
Classifier: License :: OSI Approved :: BSD License
Classifier: Operating System :: MacOS :: MacOS X
Classifier: Operating System :: Microsoft :: Windows
Classifier: Programming Language :: Python :: 3.9
Classifier: Programming Language :: Python :: 3.10
Classifier: Programming Language :: Python :: 3.11
Classifier: Programming Language :: Python :: 3.12
Classifier: Programming Language :: Python :: 3.13
Classifier: Programming Language :: Python :: Implementation :: CPython
Classifier: Topic :: Scientific/Engineering :: Artificial Intelligence
Requires-Python: >=3.9
License-File: LICENSE
Requires-Dist: urllib3 (>=1.25)
Requires-Dist: requests
Requires-Dist: torch (>=2)
